README.rst
setup.py
katnip/__init__.py
katnip.egg-info/PKG-INFO
katnip.egg-info/SOURCES.txt
katnip.egg-info/dependency_links.txt
katnip.egg-info/pbr.json
katnip.egg-info/requires.txt
katnip.egg-info/top_level.txt
katnip/controllers/__init__.py
katnip/controllers/client/__init__.py
katnip/controllers/client/facedancer.py
katnip/controllers/client/process.py
katnip/controllers/client/ssh.py
katnip/controllers/server/__init__.py
katnip/controllers/server/frida.py
katnip/controllers/server/tcp_system.py
katnip/controllers/server/vmware.py
katnip/controllers/server/windbgcontroller.py
katnip/legos/__init__.py
katnip/legos/bittorrent.py
katnip/legos/dynamic.py
katnip/legos/json.py
katnip/legos/tlv.py
katnip/legos/url.py
katnip/legos/usb_hid.py
katnip/legos/xml.py
katnip/model/__init__.py
katnip/model/low_level/__init__.py
katnip/model/low_level/encoder.py
katnip/model/low_level/radamsa.py
katnip/model/low_level/scapy.py
katnip/monitors/__init__.py
katnip/monitors/network.py
katnip/monitors/serial.py
katnip/monitors/ssh.py
katnip/monitors/ssh_file.py
katnip/monitors/telnet.py
katnip/targets/__init__.py
katnip/targets/application.py
katnip/targets/file.py
katnip/targets/raw_udp.py
katnip/targets/serial.py
katnip/targets/ssl.py
katnip/targets/tcp.py
katnip/targets/udp.py
katnip/templates/__init__.py
katnip/templates/bittorent.py
katnip/templates/bootp.py
katnip/templates/dns.py
katnip/templates/ftp.py
katnip/templates/png.py
katnip/templates/usb.py
katnip/utils/__init__.py
katnip/utils/sshutils.py