Metadata-Version: 1.1
Name: katnip
Version: 0.2.5
Summary: Extensions for the Kitty fuzzing framework
Home-page: https://github.com/cisco-sas/katnip.git
Author: Cisco SAS team
Author-email: kitty-fuzzer@googlegroups.com
License: UNKNOWN
Keywords: fuzz,fuzzing,framework,sulley,kitty,katnip
Platform: UNKNOWN
Classifier: Programming Language :: Python
Classifier: Programming Language :: Python :: 2
Classifier: Programming Language :: Python :: 2.7
Classifier: Programming Language :: Python :: 2 :: Only
Classifier: Topic :: Security
Classifier: Topic :: Software Development :: Libraries :: Application Frameworks
Classifier: Topic :: Utilities
